pysolorie/__init__.py
pysolorie/atmospheric_transmission.py
pysolorie/exceptions.py
pysolorie/irradiance.py
pysolorie/logger.py
pysolorie/model.py
pysolorie/numerical_integration.py
pysolorie/observer.py
pysolorie/plotter.py
pysolorie/report.py
pysolorie/sun_position.py
pysolorie-1.5.8.dist-info/LICENSE
pysolorie-1.5.8.dist-info/METADATA
pysolorie-1.5.8.dist-info/WHEEL
pysolorie-1.5.8.dist-info/top_level.txt
pysolorie-1.5.8.dist-info/RECORD
