Metadata-Version: 2.1
Name: pysolorie
Version: 1.5.8
Summary: Orientation Analysis of Solar Panel
Home-page: https://github.com/aaghamohammadi/pysolorie
Author: Alireza Aghamohammadi
Author-email: "Alireza Aghamohammadi" <al.aghamohammadi@gmail.com>
License: {file = "LICENSE" }
Classifier: Development Status :: 5 - Production/Stable
Classifier: License :: OSI Approved :: Apache Software License
Classifier: Programming Language :: Python :: 3.9
Classifier: Programming Language :: Python :: 3.10
Classifier: Programming Language :: Python :: 3.11
Classifier: Programming Language :: Python :: Implementation :: PyPy
Classifier: Topic :: Scientific/Engineering :: Astronomy
Classifier: Topic :: Software Development :: Libraries :: Python Modules
License-File: LICENSE
Requires-Dist: matplotlib>=3.8.2
Requires-Dist: scipy>=1.11.4
